pytest_demo_lalewis1/__init__.py
pytest_demo_lalewis1/__main__.py
pytest_demo_lalewis1/main.py
pytest_demo_lalewis1-0.1.0.dist-info/METADATA
pytest_demo_lalewis1-0.1.0.dist-info/WHEEL
pytest_demo_lalewis1-0.1.0.dist-info/RECORD
