Metadata-Version: 2.1
Name: pytest-demo-lalewis1
Version: 0.1.0
Summary: 
Author: Lawson Lewis
Author-email: lawson@kurrawong.ai
Requires-Python: >=3.11,<4.0
Classifier: Programming Language :: Python :: 3
Classifier: Programming Language :: Python :: 3.11
Classifier: Programming Language :: Python :: 3.12
Requires-Dist: pytest (>=8.0.0,<9.0.0)
